oxeye-0.1.1.dist-info/METADATA
oxeye-0.1.1.dist-info/WHEEL
oxeye-0.1.1.dist-info/entry_points.txt
oxeye-0.1.1.dist-info/licenses/LICENSE
oxeye.pyi
oxeye/__init__.py
oxeye/__init__.pyi
oxeye/oxeye.cpython-313-darwin.so
oxeye/py.typed
oxeye-0.1.1.dist-info/RECORD
