Metadata-Version: 2.4
Name: oxeye
Version: 0.1.1
Classifier: Development Status :: 3 - Alpha
Classifier: Programming Language :: Rust
Classifier: Programming Language :: Python :: Implementation :: CPython
Classifier: Operating System :: OS Independent
Classifier: Intended Audience :: Developers
Classifier: Topic :: Software Development :: Libraries :: Python Modules
License-File: LICENSE
Summary: Language Server Protocol server for Simplicity High-Level blockchain programming language
Author-email: Sitt Guruvanich <aekasitt.g@siamintech.co.th>
Requires-Python: >=3.9
